tracex_parser/__init__.py
tracex_parser/events.py
tracex_parser/file_parser.py
tracex_parser/helpers.py
tracex_parser-3.0.1.dist-info/METADATA
tracex_parser-3.0.1.dist-info/WHEEL
tracex_parser-3.0.1.dist-info/entry_points.txt
tracex_parser-3.0.1.dist-info/RECORD
