Metadata-Version: 2.1
Name: tracex_parser
Version: 3.0.1
Summary: Parser for ThreadX RTOS's trace buffers (aka TraceX)
License: MIT
Author: Julianne Swinoga
Author-email: julianneswinoga@gmail.com
Requires-Python: >=3.8.1,<4.0.0
Classifier: License :: OSI Approved :: MIT License
Classifier: Programming Language :: Python :: 3
Classifier: Programming Language :: Python :: 3.9
Classifier: Programming Language :: Python :: 3.10
Classifier: Programming Language :: Python :: 3.11
Classifier: Programming Language :: Python :: 3.12
Classifier: Programming Language :: Python :: 3.13
Project-URL: Bug Tracker, https://github.com/julianneswinoga/tracex_parser/issues
Project-URL: Documentation, https://tracex_parser.readthedocs.io/en/latest
Project-URL: Repository, https://github.com/julianneswinoga/tracex_parser
